rankexpansion/__init__.py
rankexpansion/extraction_utils.py
rankexpansion/query_expansion.py
rankexpansion/ranking_system.py
rankexpansion/tests/test_extraction_utils.py
rankexpansion/tests/test_query_expansion.py
rankexpansion/tests/test_ranking_system.py
rankexpansion-0.0.27.dist-info/METADATA
rankexpansion-0.0.27.dist-info/WHEEL
rankexpansion-0.0.27.dist-info/top_level.txt
rankexpansion-0.0.27.dist-info/RECORD
