Metadata-Version: 2.1
Name: rankexpansion
Version: 0.0.27
Author: Ashwin P N
Author-email: ashwin@talentium.io
License: MIT
Classifier: Programming Language :: Python :: 3
Classifier: License :: OSI Approved :: MIT License
Classifier: Operating System :: OS Independent
Requires-Dist: geopy ==2.3.0
Requires-Dist: nltk ==3.8.1
Requires-Dist: numpy >=1.18
Requires-Dist: openai ==0.27.8
Requires-Dist: packaging ==23.1
Requires-Dist: searchdatamodels >=0.0.39
Requires-Dist: sentence-transformers ==2.2.2
Requires-Dist: spacy ==3.6.1
Requires-Dist: transformers ==4.31.0
Requires-Dist: mongomock ==4.1.2
Requires-Dist: fastapi ==0.97.0
Requires-Dist: pymongo ==4.5.0
Requires-Dist: munch >=4.0.0
Requires-Dist: talentiumkg >=0.0.9
